[
    {
        "Image": "blog-01.jpg"
    },
    {
        "Image": "blog-02.jpg"
    },
    {
        "Image": "blog-03.jpg"
    },
    {
        "Image": "blog-04.jpg"
    },
    {
        "Image": "blog-01.jpg"
    },
    {
        "Image": "blog-02.jpg"
    },
    {
        "Image": "blog-03.jpg"
    },
    {
        "Image": "blog-04.jpg"
    },
    {
        "Image": "blog-01.jpg"
    },
    {
        "Image": "blog-02.jpg"
    },
    {
        "Image": "blog-03.jpg"
    },
    {
        "Image": "blog-04.jpg"
    }
]